[{"words":[{"a":"ٱنفِرُواْ","p":"infiru","b":"তোমরা বের হও"},{"a":"خِفَافٗا","p":"khifafan","b":"হালকা অবস্থায় (থাকো)"},{"a":"وَثِقَالٗا","p":"wathiqalan","b":"কিংবা ভারী অবস্থায়"},{"a":"وَجَٰهِدُواْ","p":"wajahidu","b":"এবং তোমরা জিহাদ করো"},{"a":"بِأَمۡوَٰلِكُمۡ","p":"bi-amwalikum","b":"দিয়ে ধনসম্পদ তোমাদের"},{"a":"وَأَنفُسِكُمۡ","p":"wa-anfusikum","b":"ও জান-প্রাণ (দিয়ে) তোমাদের"},{"a":"فِي","p":"fi","b":"মধ্যে"},{"a":"سَبِيلِ","p":"sabili","b":"পথের"},{"a":"ٱللَّهِۚ","p":"al-lahi","b":"আল্লাহর"},{"a":"ذَٰلِكُمۡ","p":"dhalikum","b":"(তোমাদের) সেটাই"},{"a":"خَيۡرٞ","p":"khayrun","b":"উত্তম"},{"a":"لَّكُمۡ","p":"lakum","b":"জন্যে তোমাদের"},{"a":"إِن","p":"in","b":"যদি"},{"a":"كُنتُمۡ","p":"kuntum","b":"তোমরা ছিলে"},{"a":"تَعۡلَمُونَ","p":"ta'lamuna","b":"জানতে"}],"translation":"তোমরা বের হয়ে পড় স্বল্প বা প্রচুর সরঞ্জামের সাথে এবং জেহাদ কর আল্লাহর পথে নিজেদের মাল ও জান দিয়ে, এটি তোমাদের জন্যে অতি উত্তম, যদি তোমরা বুঝতে পার।"},{"words":[{"a":"لَوۡ","p":"law","b":"যদি"},{"a":"كَانَ","p":"kana","b":"হতো"},{"a":"عَرَضٗا","p":"aradan","b":"সম্পদ লাভের আশা"},{"a":"قَرِيبٗا","p":"qariban","b":"নিকটবর্তী (সহজলভ্য)"},{"a":"وَسَفَرٗا","p":"wasafaran","b":"ও ভ্রমণ"},{"a":"قَاصِدٗا","p":"qasidan","b":"সুগম"},{"a":"لَّٱتَّبَعُوكَ","p":"la-ittaba'uka","b":"অবশ্যই তোমাকে তারা অনুসরণ করতো"},{"a":"وَلَٰكِنۢ","p":"walakin","b":"কিন্তু"},{"a":"بَعُدَتۡ","p":"ba'udat","b":"দীর্ঘ লাগলো"},{"a":"عَلَيۡهِمُ","p":"alayhimu","b":"কাছে তাদের"},{"a":"ٱلشُّقَّةُۚ","p":"al-shuqatu","b":"কষ্টসাধ্য যাত্রাপথ"},{"a":"وَسَيَحۡلِفُونَ","p":"wasayahlifuna","b":"ও (এখন)অচিরেই তারা শপথ করে বলবে"},{"a":"بِٱللَّهِ","p":"bil-lahi","b":"নামে আল্লাহর"},{"a":"لَوِ","p":"lawi","b":"\"যদি"},{"a":"ٱسۡتَطَعۡنَا","p":"is'tata'na","b":"পারতাম আমরা"},{"a":"لَخَرَجۡنَا","p":"lakharajna","b":"অবশ্যই বের হতাম আমরা"},{"a":"مَعَكُمۡ","p":"ma'akum","b":"সাথে তোমাদের\""},{"a":"يُهۡلِكُونَ","p":"yuh'likuna","b":"(আসলে) তারা ধ্বংস করছে"},{"a":"أَنفُسَهُمۡ","p":"anfusahum","b":"নিজেদেরকে তাদের"},{"a":"وَٱللَّهُ","p":"wal-lahu","b":"এবং আল্লাহ"},{"a":"يَعۡلَمُ","p":"ya'lamu","b":"জানেন"},{"a":"إِنَّهُمۡ","p":"innahum","b":"নিশ্চয়ই তারা"},{"a":"لَكَٰذِبُونَ","p":"lakadhibuna","b":"অবশ্যই মিথ্যাবাদী"}],"translation":"যদি আশু লাভের সম্ভাবনা থাকতো এবং যাত্রাপথও সংক্ষিপ্ত হতো, তবে তারা অবশ্যই আপনার সহযাত্রী হতো, কিন্তু তাদের নিকট যাত্রাপথ সুদীর্ঘ মনে হল। আর তারা এমনই শপথ করে বলবে, আমাদের সাধ্য থাকলে অবশ্যই তোমাদের সাথে বের হতাম, এরা নিজেরাই নিজেদের বিনষ্ট করছে, আর আল্লাহ জানেন যে, এরা মিথ্যাবাদী।"},{"words":[{"a":"عَفَا","p":"afa","b":"ক্ষমা করেছেন"},{"a":"ٱللَّهُ","p":"al-lahu","b":"আল্লাহ"},{"a":"عَنكَ","p":"anka","b":"বিষয়কে তোমার"},{"a":"لِمَ","p":"lima","b":"কেন"},{"a":"أَذِنتَ","p":"adhinta","b":"অব্যহতি দিলে"},{"a":"لَهُمۡ","p":"lahum","b":"তাদেরকে"},{"a":"حَتَّىٰ","p":"hatta","b":"যতক্ষণ না"},{"a":"يَتَبَيَّنَ","p":"yatabayyana","b":"সুস্পষ্ট হয়ে যায়"},{"a":"لَكَ","p":"laka","b":"কাছে তোমার"},{"a":"ٱلَّذِينَ","p":"alladhina","b":"যারা"},{"a":"صَدَقُواْ","p":"sadaqu","b":"সত্য বলেছে"},{"a":"وَتَعۡلَمَ","p":"wata'lama","b":"ও তুমি জানতে পারো"},{"a":"ٱلۡكَٰذِبِينَ","p":"al-kadhibina","b":"মিথ্যাবাদীদেরকে"}],"translation":"আল্লাহ আপনাকে ক্ষমা করুন, আপনি কেন তাদের অব্যাহতি দিলেন, যে পর্যন্ত না আপনার কাছে পরিষ্কার হয়ে যেত সত্যবাদীরা এবং জেনে নিতেন মিথ্যাবাদীদের।"},{"words":[{"a":"لَا","p":"la","b":"না"},{"a":"يَسۡتَـٔۡذِنُكَ","p":"yastadhinuka","b":"তোমার কাছে অব্যহতি চায়"},{"a":"ٱلَّذِينَ","p":"alladhina","b":"(তারা) যারা"},{"a":"يُؤۡمِنُونَ","p":"yu'minuna","b":"ঈমান আনে"},{"a":"بِٱللَّهِ","p":"bil-lahi","b":"উপর আল্লাহর"},{"a":"وَٱلۡيَوۡمِ","p":"wal-yawmi","b":"ও দিনে"},{"a":"ٱلۡأٓخِرِ","p":"al-akhiri","b":"আখেরাতের (উপর)"},{"a":"أَن","p":"an","b":"যে"},{"a":"يُجَٰهِدُواْ","p":"yujahidu","b":"তারা জিহাদ করবে (না)"},{"a":"بِأَمۡوَٰلِهِمۡ","p":"bi-amwalihim","b":"দিয়ে ধনসম্পদ তাদের"},{"a":"وَأَنفُسِهِمۡۗ","p":"wa-anfusihim","b":"ও জান-প্রাণ তাদের (দিয়ে)"},{"a":"وَٱللَّهُ","p":"wal-lahu","b":"এবং আল্লাহ"},{"a":"عَلِيمُۢ","p":"alimun","b":"খুব জানেন"},{"a":"بِٱلۡمُتَّقِينَ","p":"bil-mutaqina","b":"সম্পর্কে মুত্তাকীদের"}],"translation":"আল্লাহ ও রোজ কেয়ামতের প্রতি যাদের ঈমান রয়েছে তারা মাল ও জান দ্বারা জেহাদ করা থেকে আপনার কাছে অব্যাহতি কামনা করবে না, আর আল্লাহ সাবধানীদের ভাল জানেন।"},{"words":[{"a":"إِنَّمَا","p":"innama","b":"প্রকৃতপক্ষে"},{"a":"يَسۡتَـٔۡذِنُكَ","p":"yastadhinuka","b":"তোমার কাছে অব্যহতি চায়"},{"a":"ٱلَّذِينَ","p":"alladhina","b":"(তারাই) যারা"},{"a":"لَا","p":"la","b":"না"},{"a":"يُؤۡمِنُونَ","p":"yu'minuna","b":"ঈমান আনে"},{"a":"بِٱللَّهِ","p":"bil-lahi","b":"উপর আল্লাহর"},{"a":"وَٱلۡيَوۡمِ","p":"wal-yawmi","b":"ও দিনে"},{"a":"ٱلۡأٓخِرِ","p":"al-akhiri","b":"আখেরাতের (উপর)"},{"a":"وَٱرۡتَابَتۡ","p":"wa-ir'tabat","b":"এবং সন্দেহে পড়েছে"},{"a":"قُلُوبُهُمۡ","p":"qulubuhum","b":"অন্তর তাদের"},{"a":"فَهُمۡ","p":"fahum","b":"তাই তারা"},{"a":"فِي","p":"fi","b":"মধ্যে"},{"a":"رَيۡبِهِمۡ","p":"raybihim","b":"সন্দেহের তাদের"},{"a":"يَتَرَدَّدُونَ","p":"yataraddaduna","b":"তারা দ্বিধাগ্রস্ত হচ্ছে"}],"translation":"নিঃসন্দেহে তারাই আপনার কাছে অব্যাহতি চায়, যারা আল্লাহ ও রোজ কেয়ামতে ঈমান রাখে না এবং তাদের অন্তর সন্দেহগ্রস্ত হয়ে পড়েছে, সুতরাং সন্দেহের আবর্তে তারা ঘুরপাক খেয়ে চলেছে।"},{"words":[{"a":"۞وَلَوۡ","p":"walaw","b":"এবং যদি"},{"a":"أَرَادُواْ","p":"aradu","b":"তারা ইচ্ছা করতো"},{"a":"ٱلۡخُرُوجَ","p":"al-khuruja","b":"বের হওয়ার"},{"a":"لَأَعَدُّواْ","p":"la-a'addu","b":"তারা অবশ্যই প্রস্তুতি নিতো"},{"a":"لَهُۥ","p":"lahu","b":"জন্যে তার"},{"a":"عُدَّةٗ","p":"uddatan","b":"প্রস্তুতি (যথাযথ)"},{"a":"وَلَٰكِن","p":"walakin","b":"কিন্তু"},{"a":"كَرِهَ","p":"kariha","b":"অপছন্দ করেছেন"},{"a":"ٱللَّهُ","p":"al-lahu","b":"আল্লাহ"},{"a":"ٱنۢبِعَاثَهُمۡ","p":"inbi'athahum","b":"অভিযাত্রা তাদের"},{"a":"فَثَبَّطَهُمۡ","p":"fathabbatahum","b":"অতঃপর বিরত রাখলেন তাদেরকে"},{"a":"وَقِيلَ","p":"waqila","b":"এবং বলা হলো"},{"a":"ٱقۡعُدُواْ","p":"uq'udu","b":"\"তোমরা বসে থাকো"},{"a":"مَعَ","p":"ma'a","b":"সাথে"},{"a":"ٱلۡقَٰعِدِينَ","p":"al-qa'idina","b":"বসে থাকা লোকদের\""}],"translation":"আর যদি তারা বের হবার সংকল্প নিত, তবে অবশ্যই কিছু সরঞ্জাম প্রস্তুত করতো। কিন্তু তাদের উত্থান আল্লাহর পছন্দ নয়, তাই তাদের নিবৃত রাখলেন এবং আদেশ হল বসা লোকদের সাথে তোমরা বসে থাক।"},{"words":[{"a":"لَوۡ","p":"law","b":"যদি"},{"a":"خَرَجُواْ","p":"kharaju","b":"তারা বের হতো"},{"a":"فِيكُم","p":"fikum","b":"মধ্যে তোমাদের"},{"a":"مَّا","p":"ma","b":"না"},{"a":"زَادُوكُمۡ","p":"zadukum","b":"তোমাদের মধ্যে বাড়াতো (আর কিছু)"},{"a":"إِلَّا","p":"illa","b":"এ ছাড়া"},{"a":"خَبَالٗا","p":"khabalan","b":"বিভ্রান্তি"},{"a":"وَلَأَوۡضَعُواْ","p":"wala-awda'u","b":"এবং অবশ্যই তারা ঘোড়া দৌড়াতো (ছুটাছুটি করতো)"},{"a":"خِلَٰلَكُمۡ","p":"khilalakum","b":"মাঝে তোমাদের"},{"a":"يَبۡغُونَكُمُ","p":"yabghunakumu","b":"তোমাদের মধ্যে তারা চাইতো"},{"a":"ٱلۡفِتۡنَةَ","p":"al-fit'nata","b":"বিপর্যয় (সৃষ্টি করতে)"},{"a":"وَفِيكُمۡ","p":"wafikum","b":"এবং মধ্যে তোমাদের (আছে)"},{"a":"سَمَّـٰعُونَ","p":"samma'una","b":"গুপ্তচর (কান দেয়ার লোক)"},{"a":"لَهُمۡۗ","p":"lahum","b":"জন্যে তাদের"},{"a":"وَٱللَّهُ","p":"wal-lahu","b":"এবং আল্লাহ"},{"a":"عَلِيمُۢ","p":"alimun","b":"খুব জানেন"},{"a":"بِٱلظَّـٰلِمِينَ","p":"bil-zalimina","b":"সম্পর্কে সীমালঙ্ঘনকারীদের"}],"translation":"যদি তোমাদের সাথে তারা বের হত, তবে তোমাদের অনিষ্ট ছাড়া আর কিছু বৃদ্ধি করতো না, আর অশ্ব ছুটাতো তোমাদের মধ্যে বিভেদ সৃষ্টির উদ্দেশে। আর তোমাদের মাঝে রয়েছে তাদের গুপ্তচর। বস্তুতঃ আল্লাহ যালিমদের ভালভাবেই জানেন।"},{"words":[{"a":"لَقَدِ","p":"laqadi","b":"নিশ্চয়ই"},{"a":"ٱبۡتَغَوُاْ","p":"ib'taghawu","b":"তারা চেয়েছিলো"},{"a":"ٱلۡفِتۡنَةَ","p":"al-fit'nata","b":"বিপর্যয়(সৃষ্টি করতে)"},{"a":"مِن","p":"min","b":"থেকেও"},{"a":"قَبۡلُ","p":"qablu","b":"পূর্ব"},{"a":"وَقَلَّبُواْ","p":"waqallabu","b":"এবং উল্টাপাল্টা করেছে"},{"a":"لَكَ","p":"laka","b":"জন্যে তোমার"},{"a":"ٱلۡأُمُورَ","p":"al-umura","b":"কাজ-কর্ম"},{"a":"حَتَّىٰ","p":"hatta","b":"যতক্ষণ না"},{"a":"جَآءَ","p":"jaa","b":"এসেছে"},{"a":"ٱلۡحَقُّ","p":"al-haqu","b":"সত্য"},{"a":"وَظَهَرَ","p":"wazahara","b":"ও বিজয়ী হয়েছে"},{"a":"أَمۡرُ","p":"amru","b":"নির্দেশ"},{"a":"ٱللَّهِ","p":"al-lahi","b":"আল্লাহর"},{"a":"وَهُمۡ","p":"wahum","b":"অথচ তারা"},{"a":"كَٰرِهُونَ","p":"karihuna","b":"অপছন্দকারী"}],"translation":"তারা পূর্বে থেকেই বিভেদ সৃষ্টির সুযোগ সন্ধানে ছিল এবং আপনার কার্যসমূহ উল্টা-পাল্টা করে দিচ্ছিল। শেষ পর্যন্ত সত্য প্রতিশ্রুতি এসে গেল এবং জয়ী হল আল্লাহর হুকুম, যে অবস্থায় তারা মন্দবোধ করল।"},{"words":[{"a":"وَمِنۡهُم","p":"wamin'hum","b":"ও মধ্যে তাদের(এমনও আছে)"},{"a":"مَّن","p":"man","b":"যে"},{"a":"يَقُولُ","p":"yaqulu","b":"বলে"},{"a":"ٱئۡذَن","p":"i'dhan","b":"\"অব্যাহতি দিন"},{"a":"لِّي","p":"li","b":"\"আমাকে"},{"a":"وَلَا","p":"wala","b":"এবং না"},{"a":"تَفۡتِنِّيٓۚ","p":"taftinni","b":"আমাকে বিপর্যয়ে ফেলবেন\""},{"a":"أَلَا","p":"ala","b":"সাবধান (শুনে রাখো)"},{"a":"فِي","p":"fi","b":"মধ্যে"},{"a":"ٱلۡفِتۡنَةِ","p":"al-fit'nati","b":"বিপর্যয়ের"},{"a":"سَقَطُواْۗ","p":"saqatu","b":"তারা পড়েছে"},{"a":"وَإِنَّ","p":"wa-inna","b":"এবং নিশ্চয়ই"},{"a":"جَهَنَّمَ","p":"jahannama","b":"জাহান্নাম"},{"a":"لَمُحِيطَةُۢ","p":"lamuhitatun","b":"অবশ্যই পরিবেষ্টনকারী"},{"a":"بِٱلۡكَٰفِرِينَ","p":"bil-kafirina","b":"নিয়ে কাফেরদেরকে"}],"translation":"আর তাদের কেউ বলে, আমাকে অব্যাহতি দিন এবং পথভ্রষ্ট করবেন না। শোনে রাখ, তারা তো পূর্ব থেকেই পথভ্রষ্ট এবং নিঃসন্দেহে জাহান্নাম এই কাফেরদের পরিবেষ্টন করে রয়েছে।"},{"words":[{"a":"إِن","p":"in","b":"যদি"},{"a":"تُصِبۡكَ","p":"tusib'ka","b":"তোমার পৌঁছে"},{"a":"حَسَنَةٞ","p":"hasanatun","b":"কোনো কল্যাণ"},{"a":"تَسُؤۡهُمۡۖ","p":"tasu'hum","b":"তা পীড়া দেয় তাদেরকে"},{"a":"وَإِن","p":"wa-in","b":"এবং যদি"},{"a":"تُصِبۡكَ","p":"tusib'ka","b":"তোমার পৌঁছে"},{"a":"مُصِيبَةٞ","p":"musibatun","b":"কোনো বিপদ"},{"a":"يَقُولُواْ","p":"yaqulu","b":"তারা বলে"},{"a":"قَدۡ","p":"qad","b":"\"নিশ্চয়ই"},{"a":"أَخَذۡنَآ","p":"akhadhna","b":"আমরা (সামলে নিয়েছি)"},{"a":"أَمۡرَنَا","p":"amrana","b":"কাজ আমাদের"},{"a":"مِن","p":"min","b":"থেকেই\""},{"a":"قَبۡلُ","p":"qablu","b":"পূর্ব\""},{"a":"وَيَتَوَلَّواْ","p":"wayatawallaw","b":"ও তারা ফিরে যায়"},{"a":"وَّهُمۡ","p":"wahum","b":"এ অবস্থায় যে তারা"},{"a":"فَرِحُونَ","p":"farihuna","b":"উৎফুল্ল"}],"translation":"আপনার কোন কল্যাণ হলে তারা মন্দবোধ করে এবং কোন বিপদ উপস্থিত হলে তারা বলে, আমরা পূর্ব থেকেই নিজেদের কাজ সামলে নিয়েছি এবং ফিরে যায় উল্লসিত মনে।"}]