[{"words":[{"a":"وَثَمُودَاْ","p":"wathamuda","b":"এবং সামুদকেও"},{"a":"فَمَآ","p":"fama","b":"অতঃপর না"},{"a":"أَبۡقَىٰ","p":"abqa","b":"অবশিষ্ট রেখেছেন"}],"translation":"এবং সামুদকেও; অতঃপর কাউকে অব্যহতি দেননি।"},{"words":[{"a":"وَقَوۡمَ","p":"waqawma","b":"এবং জাতিকে"},{"a":"نُوحٖ","p":"nuhin","b":"নূহের"},{"a":"مِّن","p":"min","b":"থেকে"},{"a":"قَبۡلُۖ","p":"qablu","b":"ইতিপূর্বে(ধংস করেছেন)"},{"a":"إِنَّهُمۡ","p":"innahum","b":"তারা নিশ্চয়ই"},{"a":"كَانُواْ","p":"kanu","b":"ছিল"},{"a":"هُمۡ","p":"hum","b":"তারা"},{"a":"أَظۡلَمَ","p":"azlama","b":"বড়ই সীমালঙ্ঘনকারী"},{"a":"وَأَطۡغَىٰ","p":"wa-atgha","b":"ও অতি অবাধ্য"}],"translation":"এবং তাদের পূর্বে নূহের সম্প্রদায়কে, তারা ছিল আরও জালেম ও অবাধ্য।"},{"words":[{"a":"وَٱلۡمُؤۡتَفِكَةَ","p":"wal-mu'tafikata","b":"এবং উল্টে দেওয়া জনবসতিসমূহকে"},{"a":"أَهۡوَىٰ","p":"ahwa","b":"শূন্যে তুলে নিক্ষেপ করেছিলেন"}],"translation":"তিনিই জনপদকে শুন্যে উত্তোলন করে নিক্ষেপ করেছেন।"},{"words":[{"a":"فَغَشَّىٰهَا","p":"faghashaha","b":"তাকে অতঃপর ঢেকে দিল"},{"a":"مَا","p":"ma","b":"যা"},{"a":"غَشَّىٰ","p":"ghasha","b":"ঢেকে দেওয়ার ছিল"}],"translation":"অতঃপর তাকে আচ্ছন্ন করে নেয় যা আচ্ছন্ন করার।"},{"words":[{"a":"فَبِأَيِّ","p":"fabi-ayyi","b":"অতএব কোন"},{"a":"ءَالَآءِ","p":"alai","b":"অনুগ্রহ সমূহকে"},{"a":"رَبِّكَ","p":"rabbika","b":"তোমার রবের"},{"a":"تَتَمَارَىٰ","p":"tatamara","b":"তুমি সন্দেহ করবে"}],"translation":"অতঃপর তুমি তোমার পালনকর্তার কোন অনুগ্রহকে মিথ্যা বলবে?"},{"words":[{"a":"هَٰذَا","p":"hadha","b":"এই"},{"a":"نَذِيرٞ","p":"nadhirun","b":"সতর্কবাণীও (অন্যতম)"},{"a":"مِّنَ","p":"mina","b":"মধ্য হতে"},{"a":"ٱلنُّذُرِ","p":"al-nudhuri","b":"সতর্কবাণী সমূহের"},{"a":"ٱلۡأُولَىٰٓ","p":"al-ula","b":"অতীতের (আসা)"}],"translation":"অতীতের সতর্ককারীদের মধ্যে সে-ও একজন সতর্ককারী।"},{"words":[{"a":"أَزِفَتِ","p":"azifati","b":"নিকটে এসেছে"},{"a":"ٱلۡأٓزِفَةُ","p":"al-azifatu","b":"নিকটে আগমনকারী (মুহূর্ত অর্থাৎ কিয়ামাত)"}],"translation":"কেয়ামত নিকটে এসে গেছে।"},{"words":[{"a":"لَيۡسَ","p":"laysa","b":"নেই"},{"a":"لَهَا","p":"laha","b":"তার জন্যে"},{"a":"مِن","p":"min","b":"মধ্য হতে"},{"a":"دُونِ","p":"duni","b":"ছাড়া"},{"a":"ٱللَّهِ","p":"al-lahi","b":"আল্লাহ"},{"a":"كَاشِفَةٌ","p":"kashifatun","b":"কোনো প্রকাশকারী"}],"translation":"আল্লাহ ব্যতীত কেউ একে প্রকাশ করতে সক্ষম নয়।"},{"words":[{"a":"أَفَمِنۡ","p":"afamin","b":"তবে কি হতে"},{"a":"هَٰذَا","p":"hadha","b":"এই"},{"a":"ٱلۡحَدِيثِ","p":"al-hadithi","b":"কথা"},{"a":"تَعۡجَبُونَ","p":"ta'jabuna","b":"তোমরা অবাক হচ্ছ"}],"translation":"তোমরা কি এই বিষয়ে আশ্চর্যবোধ করছ?"},{"words":[{"a":"وَتَضۡحَكُونَ","p":"watadhakuna","b":"এবং তোমরা হাসি ঠাট্টা করছ"},{"a":"وَلَا","p":"wala","b":"অথচ না"},{"a":"تَبۡكُونَ","p":"tabkuna","b":"তোমরা কাঁদছ"}],"translation":"এবং হাসছ-ক্রন্দন করছ না?"}]