[{"words":[{"a":"وَإِنَّ","p":"wa-inna","b":"এবং নিশ্চয়ই"},{"a":"لَكُمۡ","p":"lakum","b":"জন্যে তোমাদের"},{"a":"فِي","p":"fi","b":"মধ্যে (আছে)"},{"a":"ٱلۡأَنۡعَٰمِ","p":"al-an'ami","b":"গৃহপালিত পশুদের"},{"a":"لَعِبۡرَةٗۖ","p":"la'ib'ratan","b":"অবশ্যই শিক্ষা"},{"a":"نُّسۡقِيكُم","p":"nus'qikum","b":"তোমাদেরকে পান করাই আমরা"},{"a":"مِّمَّا","p":"mimma","b":"তা হ'তে যা"},{"a":"فِي","p":"fi","b":"রয়েছে"},{"a":"بُطُونِهَا","p":"butuniha","b":"তাদের পেটে (অর্থাৎ দুধ)"},{"a":"وَلَكُمۡ","p":"walakum","b":"আর জন্যে তোমাদের (রয়েছে)"},{"a":"فِيهَا","p":"fiha","b":"তাদের মধ্যে"},{"a":"مَنَٰفِعُ","p":"manafi'u","b":"উপকারিতা"},{"a":"كَثِيرَةٞ","p":"kathiratun","b":"প্রচুর"},{"a":"وَمِنۡهَا","p":"wamin'ha","b":"আর তাদের মধ্য হ'তে"},{"a":"تَأۡكُلُونَ","p":"takuluna","b":"তোমরা খাও (গোশত)"}],"translation":"এবং তোমাদের জন্যে চতুস্পদ জন্তু সমূহের মধ্যে চিন্তা করার বিষয় রয়েছে। আমি তোমাদেরকে তাদের উদরস্থিত বস্তু থেকে পান করাই এবং তোমাদের জন্যে তাদের মধ্যে প্রচুর উপকারিতা আছে। তোমরা তাদের কতককে ভক্ষণ কর।"},{"words":[{"a":"وَعَلَيۡهَا","p":"wa'alayha","b":"এবং তাদের উপর"},{"a":"وَعَلَى","p":"wa'ala","b":"ও উপর"},{"a":"ٱلۡفُلۡكِ","p":"al-ful'ki","b":"নৌযানের"},{"a":"تُحۡمَلُونَ","p":"tuh'maluna","b":"তোমাদের বহন করা হয়"}],"translation":"তাদের পিঠে ও জলযানে তোমরা আরোহণ করে চলাফেরা করে থাক।"},{"words":[{"a":"وَلَقَدۡ","p":"walaqad","b":"আর নিশ্চয়ই"},{"a":"أَرۡسَلۡنَا","p":"arsalna","b":"আমরা পাঠিয়েছি"},{"a":"نُوحًا","p":"nuhan","b":"নূহকে"},{"a":"إِلَىٰ","p":"ila","b":"প্রতি"},{"a":"قَوۡمِهِۦ","p":"qawmihi","b":"তার জাতির"},{"a":"فَقَالَ","p":"faqala","b":"তখন সে বলেছিলো"},{"a":"يَٰقَوۡمِ","p":"yaqawmi","b":"\"হে আমার জাতি"},{"a":"ٱعۡبُدُواْ","p":"u'budu","b":"তোমরা ইবাদাত করো"},{"a":"ٱللَّهَ","p":"al-laha","b":"আল্লাহর"},{"a":"مَا","p":"ma","b":"নেই"},{"a":"لَكُم","p":"lakum","b":"জন্যে তোমাদের"},{"a":"مِّنۡ","p":"min","b":"কোন"},{"a":"إِلَٰهٍ","p":"ilahin","b":"ইলাহ"},{"a":"غَيۡرُهُۥٓۚ","p":"ghayruhu","b":"তিনি ছাড়া"},{"a":"أَفَلَا","p":"afala","b":"কি তবুও না"},{"a":"تَتَّقُونَ","p":"tattaquna","b":"তোমরা সাবধান হবে\""}],"translation":"আমি নূহকে তার সম্প্রদায়ের কাছে প্রেরণ করেছিলাম। সে বলেছিলঃ হে আমার সম্প্রদায়, তোমরা আল্লাহর বন্দেগী কর। তিনি ব্যতীত তোমাদের কোন মাবুদ নেই। তোমরা কি ভয় কর না।"},{"words":[{"a":"فَقَالَ","p":"faqala","b":"তখন বলেছিলো"},{"a":"ٱلۡمَلَؤُاْ","p":"al-mala-u","b":"প্রধান ব্যক্তিরা"},{"a":"ٱلَّذِينَ","p":"alladhina","b":"(তাদের) যারা"},{"a":"كَفَرُواْ","p":"kafaru","b":"অস্বীকার করেছিলো"},{"a":"مِن","p":"min","b":"মধ্য হ'তে"},{"a":"قَوۡمِهِۦ","p":"qawmihi","b":"তার জাতির"},{"a":"مَا","p":"ma","b":"\"নয়"},{"a":"هَٰذَآ","p":"hadha","b":"\"এই (ব্যক্তি)"},{"a":"إِلَّا","p":"illa","b":"এ ছাড়া যে"},{"a":"بَشَرٞ","p":"basharun","b":"একজন মানুষ"},{"a":"مِّثۡلُكُمۡ","p":"mith'lukum","b":"তোমাদেরই মতো"},{"a":"يُرِيدُ","p":"yuridu","b":"সে চায়"},{"a":"أَن","p":"an","b":"যে"},{"a":"يَتَفَضَّلَ","p":"yatafaddala","b":"শ্রেষ্ঠত্ব লাভ করবে"},{"a":"عَلَيۡكُمۡ","p":"alaykum","b":"তোমাদের উপর"},{"a":"وَلَوۡ","p":"walaw","b":"আর যদি"},{"a":"شَآءَ","p":"shaa","b":"চাইতেন"},{"a":"ٱللَّهُ","p":"al-lahu","b":"আল্লাহ্‌"},{"a":"لَأَنزَلَ","p":"la-anzala","b":"অবশ্যই পাঠাতেন"},{"a":"مَلَـٰٓئِكَةٗ","p":"malaikatan","b":"ফেরেশতা"},{"a":"مَّا","p":"ma","b":"না"},{"a":"سَمِعۡنَا","p":"sami'na","b":"আমরা শুনেছি"},{"a":"بِهَٰذَا","p":"bihadha","b":"ধরণের এ (কথা)"},{"a":"فِيٓ","p":"fi","b":"মধ্যে"},{"a":"ءَابَآئِنَا","p":"abaina","b":"আমাদের পিতৃপুরুষদের"},{"a":"ٱلۡأَوَّلِينَ","p":"al-awalina","b":"পূর্বকালের"}],"translation":"তখন তার সম্প্রদায়ের কাফের-প্রধানরা বলেছিলঃ এ তো তোমাদের মতই একজন মানুষ বৈ নয়। সে তোমাদের উপর নেতৃত্ব করতে চায়। আল্লাহ ইচ্ছা করলে ফেরেশতাই নাযিল করতেন। আমরা আমাদের পূর্বপুরুষদের মধ্যে এরূপ কথা শুনিনি।"},{"words":[{"a":"إِنۡ","p":"in","b":"নয়"},{"a":"هُوَ","p":"huwa","b":"সে"},{"a":"إِلَّا","p":"illa","b":"এ ছাড়া যে"},{"a":"رَجُلُۢ","p":"rajulun","b":"একজন মানুষ"},{"a":"بِهِۦ","p":"bihi","b":"সাথে তার (আছে)"},{"a":"جِنَّةٞ","p":"jinnatun","b":"জ্বিন"},{"a":"فَتَرَبَّصُواْ","p":"fatarabbasu","b":"অতএব তোমরা অপেক্ষা করো"},{"a":"بِهِۦ","p":"bihi","b":"সম্পর্কে তার"},{"a":"حَتَّىٰ","p":"hatta","b":"পর্যন্ত"},{"a":"حِينٖ","p":"hinin","b":"কিছুকাল\""}],"translation":"সে তো এক উম্মাদ ব্যক্তি বৈ নয়। সুতরাং কিছুকাল তার ব্যাপারে অপেক্ষা কর।"},{"words":[{"a":"قَالَ","p":"qala","b":"(নূহ) বললো"},{"a":"رَبِّ","p":"rabbi","b":"\"হে আমার রব"},{"a":"ٱنصُرۡنِي","p":"unsur'ni","b":"আমাকে সাহায্য করো"},{"a":"بِمَا","p":"bima","b":"এ কারণে যে"},{"a":"كَذَّبُونِ","p":"kadhabuni","b":"আমাকে তারা মিথ্যা সাব্যস্ত করেছে\""}],"translation":"নূহ বলেছিলঃ হে আমার পালনকর্তা, আমাকে সাহায্য কর; কেননা, তারা আমাকে মিথ্যাবাদী বলছে।"},{"words":[{"a":"فَأَوۡحَيۡنَآ","p":"fa-awhayna","b":"অতঃপর আমরা ওহী করলাম"},{"a":"إِلَيۡهِ","p":"ilayhi","b":"তার প্রতি"},{"a":"أَنِ","p":"ani","b":"\"যে"},{"a":"ٱصۡنَعِ","p":"is'na'i","b":"নির্মাণ করো"},{"a":"ٱلۡفُلۡكَ","p":"al-ful'ka","b":"নৌকা"},{"a":"بِأَعۡيُنِنَا","p":"bi-a'yunina","b":"সামনে আমাদের চোখের"},{"a":"وَوَحۡيِنَا","p":"wawahyina","b":"ও আমাদের ওহীর ভিত্তিতে"},{"a":"فَإِذَا","p":"fa-idha","b":"অতঃপর যখন"},{"a":"جَآءَ","p":"jaa","b":"আসবে"},{"a":"أَمۡرُنَا","p":"amruna","b":"আমাদের নির্দেশ"},{"a":"وَفَارَ","p":"wafara","b":"ও উথলে উঠবে"},{"a":"ٱلتَّنُّورُ","p":"al-tanuru","b":"চুলাটি"},{"a":"فَٱسۡلُكۡ","p":"fa-us'luk","b":"(নৌকাতে) তখন উঠিয়ে নিবে"},{"a":"فِيهَا","p":"fiha","b":"তার মধ্যে"},{"a":"مِن","p":"min","b":"ধরণের"},{"a":"كُلّٖ","p":"kullin","b":"প্রত্যেক (জীব জন্তুর)"},{"a":"زَوۡجَيۡنِ","p":"zawjayni","b":"জোড়া"},{"a":"ٱثۡنَيۡنِ","p":"ith'nayni","b":"দুইটার (অর্থাৎ নর ও নারী)"},{"a":"وَأَهۡلَكَ","p":"wa-ahlaka","b":"ও তোমার পরিবারকে"},{"a":"إِلَّا","p":"illa","b":"ছাড়া"},{"a":"مَن","p":"man","b":"তাদের"},{"a":"سَبَقَ","p":"sabaqa","b":"পূর্বে নির্ধারিত হয়েছে"},{"a":"عَلَيۡهِ","p":"alayhi","b":"যাদের সম্পর্কে"},{"a":"ٱلۡقَوۡلُ","p":"al-qawlu","b":"বাণী (সিদ্ধান্ত)"},{"a":"مِنۡهُمۡۖ","p":"min'hum","b":"তাদের মধ্য হ'তে"},{"a":"وَلَا","p":"wala","b":"এবং না"},{"a":"تُخَٰطِبۡنِي","p":"tukhatib'ni","b":"আমাকে কিছু বলো"},{"a":"فِي","p":"fi","b":"সম্পর্কে"},{"a":"ٱلَّذِينَ","p":"alladhina","b":"(তাদের) যারা"},{"a":"ظَلَمُوٓاْ","p":"zalamu","b":"অত্যাচার করেছে"},{"a":"إِنَّهُم","p":"innahum","b":"তারা নিশ্চয়ই"},{"a":"مُّغۡرَقُونَ","p":"mugh'raquna","b":"নিমজ্জিত হবে"}],"translation":"অতঃপর আমি তার কাছে আদেশ প্রেরণ করলাম যে, তুমি আমার দৃষ্টির সামনে এবং আমার নির্দেশে নৌকা তৈরী কর। এরপর যখন আমার আদেশ আসে এবং চুল্লী প্লাবিত হয়, তখন নৌকায় তুলে নাও, প্রত্যেক জীবের এক এক জোড়া এবং তোমার পরিবারবর্গকে, তাদের মধ্যে যাদের বিপক্ষে পূর্বে সিদ্ধান্ত নেয়া হয়েছে তাদের ছাড়া। এবং তুমি জালেমদের সম্পর্কে আমাকে কিছু বলো না। নিশ্চয় তারা নিমজ্জত হবে।"},{"words":[{"a":"فَإِذَا","p":"fa-idha","b":"অতঃপর যখন"},{"a":"ٱسۡتَوَيۡتَ","p":"is'tawayta","b":"তুমি স্হির হবে"},{"a":"أَنتَ","p":"anta","b":"তুমি"},{"a":"وَمَن","p":"waman","b":"ও যারা"},{"a":"مَّعَكَ","p":"ma'aka","b":"তোমার সাথে"},{"a":"عَلَى","p":"ala","b":"উপর"},{"a":"ٱلۡفُلۡكِ","p":"al-ful'ki","b":"নৌকার"},{"a":"فَقُلِ","p":"faquli","b":"তখন বলো"},{"a":"ٱلۡحَمۡدُ","p":"al-hamdu","b":"\"সব প্রশংসা"},{"a":"لِلَّهِ","p":"lillahi","b":"জন্যে আল্লাহরই"},{"a":"ٱلَّذِي","p":"alladhi","b":"যিনি"},{"a":"نَجَّىٰنَا","p":"najjana","b":"আমাদেরকে উদ্ধার করেছেন"},{"a":"مِنَ","p":"mina","b":"হ'তে"},{"a":"ٱلۡقَوۡمِ","p":"al-qawmi","b":"জাতি"},{"a":"ٱلظَّـٰلِمِينَ","p":"al-zalimina","b":"সীমালঙ্ঘনকারী\""}],"translation":"যখন তুমি ও তোমার সঙ্গীরা নৌকায় আরোহণ করবে, তখন বলঃ আল্লাহর শোকর, যিনি আমাদেরকে জালেম সম্প্রদায়ের কবল থেকে উদ্ধার করেছেন।"},{"words":[{"a":"وَقُل","p":"waqul","b":"এবং বলো"},{"a":"رَّبِّ","p":"rabbi","b":"\"হে আমার রব"},{"a":"أَنزِلۡنِي","p":"anzil'ni","b":"আমাকে অবতরণ করাও"},{"a":"مُنزَلٗا","p":"munzalan","b":"অবতরণস্থানে"},{"a":"مُّبَارَكٗا","p":"mubarakan","b":"কল্যাণকর"},{"a":"وَأَنتَ","p":"wa-anta","b":"আর তুমি"},{"a":"خَيۡرُ","p":"khayru","b":"উত্তম"},{"a":"ٱلۡمُنزِلِينَ","p":"al-munzilina","b":"অবতীর্ণকারীদের (মধ্যে)\""}],"translation":"আরও বলঃ পালনকর্তা, আমাকে কল্যাণকর ভাবে নামিয়ে দাও, তুমি শ্রেষ্ঠ অবতারণকারী।"},{"words":[{"a":"إِنَّ","p":"inna","b":"নিশ্চয়ই"},{"a":"فِي","p":"fi","b":"মধ্যে (রয়েছে)"},{"a":"ذَٰلِكَ","p":"dhalika","b":"এর"},{"a":"لَأٓيَٰتٖ","p":"laayatin","b":"অবশ্যই নিদর্শন"},{"a":"وَإِن","p":"wa-in","b":"আর নিশ্চয়ই"},{"a":"كُنَّا","p":"kunna","b":"আমরাই ছিলাম"},{"a":"لَمُبۡتَلِينَ","p":"lamub'talina","b":"অবশ্যই পরীক্ষাকারী"}],"translation":"এতে নিদর্শনাবলী রয়েছে এবং আমি পরীক্ষাকারী।"}]