[{"words":[{"a":"إِلَّا","p":"illa","b":"ছাড়া"},{"a":"عَجُوزٗا","p":"ajuzan","b":"এক বৃদ্ধা (তার স্ত্রী)"},{"a":"فِي","p":"fi","b":"(সে ছিলো) অন্তর্ভুক্ত"},{"a":"ٱلۡغَٰبِرِينَ","p":"al-ghabirina","b":"পিছনে অবস্থানকারীদের"}],"translation":"এক বৃদ্ধা ব্যতীত, সে ছিল ধ্বংস প্রাপ্তদের অন্তর্ভুক্ত।"},{"words":[{"a":"ثُمَّ","p":"thumma","b":"এরপর"},{"a":"دَمَّرۡنَا","p":"dammarna","b":"আমরা ধ্বংস করলাম"},{"a":"ٱلۡأٓخَرِينَ","p":"al-akharina","b":"অন্যদেরকে"}],"translation":"এরপর অন্যদেরকে নিপাত করলাম।"},{"words":[{"a":"وَأَمۡطَرۡنَا","p":"wa-amtarna","b":"এবং আমরা বর্ষণ করেছিলাম"},{"a":"عَلَيۡهِم","p":"alayhim","b":"উপর তাদের"},{"a":"مَّطَرٗاۖ","p":"mataran","b":"এক বর্ষণ (শাস্তিমূলক)"},{"a":"فَسَآءَ","p":"fasaa","b":"অতএব কত নিকৃষ্ট"},{"a":"مَطَرُ","p":"mataru","b":"বর্ষণ"},{"a":"ٱلۡمُنذَرِينَ","p":"al-mundharina","b":"সতর্ককৃতদের (জন্যে)"}],"translation":"তাদের উপর এক বিশেষ বৃষ্টি বর্ষণ করলাম। ভীতি-প্রদর্শিত দের জন্যে এই বৃষ্টি ছিল কত নিকৃষ্ট।"},{"words":[{"a":"إِنَّ","p":"inna","b":"নিশ্চয়ই"},{"a":"فِي","p":"fi","b":"মধ্যে (আছে)"},{"a":"ذَٰلِكَ","p":"dhalika","b":"এর"},{"a":"لَأٓيَةٗۖ","p":"laayatan","b":"অবশ্যই নিদর্শন"},{"a":"وَمَا","p":"wama","b":"আর না"},{"a":"كَانَ","p":"kana","b":"ছিলো"},{"a":"أَكۡثَرُهُم","p":"aktharuhum","b":"অধিকাংশই তাদের"},{"a":"مُّؤۡمِنِينَ","p":"mu'minina","b":"মু'মিন"}],"translation":"নিশ্চয়ই এতে নিদর্শন রয়েছে; কিন্তু তাদের অধিকাংশই বিশ্বাসী নয়।"},{"words":[{"a":"وَإِنَّ","p":"wa-inna","b":"অথচ নিশ্চয়ই"},{"a":"رَبَّكَ","p":"rabbaka","b":"তোমার রব"},{"a":"لَهُوَ","p":"lahuwa","b":"অবশ্যই তিনি"},{"a":"ٱلۡعَزِيزُ","p":"al-'azizu","b":"পরাক্রমশালী"},{"a":"ٱلرَّحِيمُ","p":"al-rahimu","b":"পরম দয়ালু"}],"translation":"নিশ্চয়ই আপনার পালনকর্তা প্রবল পরাক্রমশালী, পরম দয়ালু।"},{"words":[{"a":"كَذَّبَ","p":"kadhaba","b":"মিথ্যারোপ করেছিলো"},{"a":"أَصۡحَٰبُ","p":"ashabu","b":"অধিবাসীরাও"},{"a":"لۡـَٔيۡكَةِ","p":"al'aykati","b":"আইকার"},{"a":"ٱلۡمُرۡسَلِينَ","p":"al-mur'salina","b":"রাসূলদেরকে"}],"translation":"বনের অধিবাসীরা পয়গম্বরগণকে মিথ্যাবাদী বলেছে।"},{"words":[{"a":"إِذۡ","p":"idh","b":"(স্মরণ করো) যখন"},{"a":"قَالَ","p":"qala","b":"বলেছিলো"},{"a":"لَهُمۡ","p":"lahum","b":"উদ্দেশ্যে তাদের"},{"a":"شُعَيۡبٌ","p":"shu'aybun","b":"শু'আইব"},{"a":"أَلَا","p":"ala","b":"\"কি না"},{"a":"تَتَّقُونَ","p":"tattaquna","b":"তোমরা ভয় করবে"}],"translation":"যখন শো’আয়ব তাদের কে বললেন, তোমরা কি ভয় কর না?"},{"words":[{"a":"إِنِّي","p":"inni","b":"নিশ্চয়ই আমি"},{"a":"لَكُمۡ","p":"lakum","b":"জন্যে তোমাদের"},{"a":"رَسُولٌ","p":"rasulun","b":"একজন রাসূল"},{"a":"أَمِينٞ","p":"aminun","b":"বিশ্বস্ত"}],"translation":"আমি তোমাদের বিশ্বস্ত পয়গম্বর।"},{"words":[{"a":"فَٱتَّقُواْ","p":"fa-ittaqu","b":"অতঃপর তোমরা ভয় করো"},{"a":"ٱللَّهَ","p":"al-laha","b":"আল্লাহকে"},{"a":"وَأَطِيعُونِ","p":"wa-ati'uni","b":"ও তোমরা আমার আনুগত্য করো"}],"translation":"অতএব, তোমরা আল্লাহকে ভয় কর এবং আমার আনুগত্য কর।"},{"words":[{"a":"وَمَآ","p":"wama","b":"আর না"},{"a":"أَسۡـَٔلُكُمۡ","p":"asalukum","b":"তোমাদের (নিকট) আমি চাচ্ছি"},{"a":"عَلَيۡهِ","p":"alayhi","b":"জন্যে এর"},{"a":"مِنۡ","p":"min","b":"কোনো"},{"a":"أَجۡرٍۖ","p":"ajrin","b":"প্রতিদান"},{"a":"إِنۡ","p":"in","b":"নেই"},{"a":"أَجۡرِيَ","p":"ajriya","b":"আমার প্রতিদান (অন্য কারো নিকট)"},{"a":"إِلَّا","p":"illa","b":"ছাড়া"},{"a":"عَلَىٰ","p":"ala","b":"নিকট"},{"a":"رَبِّ","p":"rabbi","b":"রবের"},{"a":"ٱلۡعَٰلَمِينَ","p":"al-'alamina","b":"বিশ্বজগতের"}],"translation":"আমি তোমাদের কাছে এর জন্য কোন প্রতিদান চাই না। আমার প্রতিদান তো বিশ্ব-পালনকর্তাই দেবেন।"}]