[{"words":[{"a":"وَٱللَّهُ","p":"wal-lahu","b":"এবং আল্লাহই"},{"a":"خَلَقَكُم","p":"khalaqakum","b":"তোমাদের সৃষ্টি করেছেন"},{"a":"مِّن","p":"min","b":"থেকে"},{"a":"تُرَابٖ","p":"turabin","b":"মাটি"},{"a":"ثُمَّ","p":"thumma","b":"এরপর"},{"a":"مِن","p":"min","b":"থেকে"},{"a":"نُّطۡفَةٖ","p":"nut'fatin","b":"শুক্রবিন্দু"},{"a":"ثُمَّ","p":"thumma","b":"এরপর"},{"a":"جَعَلَكُمۡ","p":"ja'alakum","b":"তোমাদেরকে বানিয়েছেন"},{"a":"أَزۡوَٰجٗاۚ","p":"azwajan","b":"জোড়া জোড়া"},{"a":"وَمَا","p":"wama","b":"এবং না"},{"a":"تَحۡمِلُ","p":"tahmilu","b":"গর্ভধারণ করে"},{"a":"مِنۡ","p":"min","b":"কোনো"},{"a":"أُنثَىٰ","p":"untha","b":"নারী"},{"a":"وَلَا","p":"wala","b":"আর না"},{"a":"تَضَعُ","p":"tada'u","b":"প্রসব করে সে"},{"a":"إِلَّا","p":"illa","b":"এ ব্যতীত"},{"a":"بِعِلۡمِهِۦۚ","p":"bi'il'mihi","b":"তাঁর জানা থাকে"},{"a":"وَمَا","p":"wama","b":"এবং না"},{"a":"يُعَمَّرُ","p":"yu'ammaru","b":"আয়ু বৃদ্ধি পায়"},{"a":"مِن","p":"min","b":"কোনো"},{"a":"مُّعَمَّرٖ","p":"mu'ammarin","b":"বয়স্কলোকের"},{"a":"وَلَا","p":"wala","b":"আর না"},{"a":"يُنقَصُ","p":"yunqasu","b":"কমিয়ে দেওয়া হয়"},{"a":"مِنۡ","p":"min","b":"হ'তে"},{"a":"عُمُرِهِۦٓ","p":"umurihi","b":"তার আয়ু"},{"a":"إِلَّا","p":"illa","b":"এ ছাড়া"},{"a":"فِي","p":"fi","b":"মধ্যে আছে"},{"a":"كِتَٰبٍۚ","p":"kitabin","b":"একটি কিতাবে (লিখিত)"},{"a":"إِنَّ","p":"inna","b":"নিশ্চয়ই"},{"a":"ذَٰلِكَ","p":"dhalika","b":"সেটা"},{"a":"عَلَى","p":"ala","b":"জন্যে"},{"a":"ٱللَّهِ","p":"al-lahi","b":"আল্লাহর"},{"a":"يَسِيرٞ","p":"yasirun","b":"(খুব)সহজ"}],"translation":"আল্লাহ তোমাদেরকে সৃষ্টি করেছেন মাটি থেকে, অতঃপর বীর্য থেকে, তারপর করেছেন তোমাদেরকে যুগল। কোন নারী গর্ভধারণ করে না এবং সন্তান প্রসব করে না; কিন্তু তাঁর জ্ঞাতসারে। কোন বয়স্ক ব্যক্তি বয়স পায় না। এবং তার বয়স হ্রাস পায় না; কিন্তু তা লিখিত আছে কিতাবে। নিশ্চয় এটা আল্লাহর পক্ষে সহজ।"},{"words":[{"a":"وَمَا","p":"wama","b":"এবং না"},{"a":"يَسۡتَوِي","p":"yastawi","b":"সমান হয়"},{"a":"ٱلۡبَحۡرَانِ","p":"al-bahrani","b":"দুই সাগর"},{"a":"هَٰذَا","p":"hadha","b":"যেমন (এটা)"},{"a":"عَذۡبٞ","p":"adhbun","b":"সুমিষ্ট"},{"a":"فُرَاتٞ","p":"furatun","b":"সুপেয়"},{"a":"سَآئِغٞ","p":"saighun","b":"সহজ পেয়"},{"a":"شَرَابُهُۥ","p":"sharabuhu","b":"তার পানীয়"},{"a":"وَهَٰذَا","p":"wahadha","b":"আর ওটা"},{"a":"مِلۡحٌ","p":"mil'hun","b":"লোনা"},{"a":"أُجَاجٞۖ","p":"ujajun","b":"বিস্বাদ"},{"a":"وَمِن","p":"wamin","b":"কিন্তু থেকে"},{"a":"كُلّٖ","p":"kullin","b":"প্রত্যেকটা"},{"a":"تَأۡكُلُونَ","p":"takuluna","b":"তোমরা খাও"},{"a":"لَحۡمٗا","p":"lahman","b":"গোশত (মাছ)"},{"a":"طَرِيّٗا","p":"tariyyan","b":"তাজা"},{"a":"وَتَسۡتَخۡرِجُونَ","p":"watastakhrijuna","b":"ও তোমরা বের করো"},{"a":"حِلۡيَةٗ","p":"hil'yatan","b":"অলংকার (অর্থাৎ মনি-মুক্তা)"},{"a":"تَلۡبَسُونَهَاۖ","p":"talbasunaha","b":"তা তোমরা পরিধান করো"},{"a":"وَتَرَى","p":"watara","b":"এবং তোমরা দেখো"},{"a":"ٱلۡفُلۡكَ","p":"al-ful'ka","b":"নৌকাগুলো"},{"a":"فِيهِ","p":"fihi","b":"তার মধ্যে"},{"a":"مَوَاخِرَ","p":"mawakhira","b":"পানিবিদীর্ণ করে চলে"},{"a":"لِتَبۡتَغُواْ","p":"litabtaghu","b":"তোমরা খোঁজ করতে পারো যেন"},{"a":"مِن","p":"min","b":"থেকে"},{"a":"فَضۡلِهِۦ","p":"fadlihi","b":"তাঁর অনুগ্রহ"},{"a":"وَلَعَلَّكُمۡ","p":"wala'allakum","b":"এবং তোমরা যাতে"},{"a":"تَشۡكُرُونَ","p":"tashkuruna","b":"কৃতজ্ঞতা প্রকাশ করো"}],"translation":"দু’টি সমুদ্র সমান হয় না-একটি মিঠা ও তৃষ্ণানিবারক এবং অপরটি লোনা। ঊভয়টি থেকেই তোমরা তাজা গোশত (মৎস) আহার কর এবং পরিধানে ব্যবহার্য গয়নাগাটি আহরণ কর। তুমি তাতে তার বুক চিরে জাহাজ চলতে দেখ, যাতে তোমরা তার অনুগ্রহ অন্বেষণ কর এবং যাতে তোমরা কৃতজ্ঞতা প্রকাশ কর।"},{"words":[{"a":"يُولِجُ","p":"yuliju","b":"তিনি প্রবেশ করান"},{"a":"ٱلَّيۡلَ","p":"al-layla","b":"রাতকে"},{"a":"فِي","p":"fi","b":"মধ্যে"},{"a":"ٱلنَّهَارِ","p":"al-nahari","b":"দিনের"},{"a":"وَيُولِجُ","p":"wayuliju","b":"এবং প্রবেশ করান"},{"a":"ٱلنَّهَارَ","p":"al-nahara","b":"দিনকে"},{"a":"فِي","p":"fi","b":"মধ্যে"},{"a":"ٱلَّيۡلِ","p":"al-layli","b":"রাতের"},{"a":"وَسَخَّرَ","p":"wasakhara","b":"এবং নিয়ন্ত্রিত করেছেন"},{"a":"ٱلشَّمۡسَ","p":"al-shamsa","b":"সূর্যকে"},{"a":"وَٱلۡقَمَرَۖ","p":"wal-qamara","b":"ও চাঁদকে"},{"a":"كُلّٞ","p":"kullun","b":"প্রত্যেকেই"},{"a":"يَجۡرِي","p":"yajri","b":"(পরিভ্রমণ করে) আবর্তন করে"},{"a":"لِأَجَلٖ","p":"li-ajalin","b":"একটি সময়ের জন্যে"},{"a":"مُّسَمّٗىۚ","p":"musamman","b":"নির্দিষ্ট"},{"a":"ذَٰلِكُمُ","p":"dhalikumu","b":"তোমাদের সেই"},{"a":"ٱللَّهُ","p":"al-lahu","b":"আল্লাহ-ই"},{"a":"رَبُّكُمۡ","p":"rabbukum","b":"তোমাদের রব"},{"a":"لَهُ","p":"lahu","b":"তাঁরই"},{"a":"ٱلۡمُلۡكُۚ","p":"al-mul'ku","b":"সার্বভৌমত্ব"},{"a":"وَٱلَّذِينَ","p":"wa-alladhina","b":"এবং যাদেরকে"},{"a":"تَدۡعُونَ","p":"tad'una","b":"তোমরা ডাকো"},{"a":"مِن","p":"min","b":"ছাড়া"},{"a":"دُونِهِۦ","p":"dunihi","b":"তাঁকে"},{"a":"مَا","p":"ma","b":"না"},{"a":"يَمۡلِكُونَ","p":"yamlikuna","b":"(তারা অধিকারী) অধিকার রাখে"},{"a":"مِن","p":"min","b":"কোনো"},{"a":"قِطۡمِيرٍ","p":"qit'mirin","b":"(তুচ্ছাতিতুচ্ছ বস্তুর) খেজুরের আঁটির পর্দা"}],"translation":"তিনি রাত্রিকে দিবসে প্রবিষ্ট করেন এবং দিবসকে রাত্রিতে প্রবিষ্ট করেন। তিনি সূর্য ও চন্দ্রকে কাজে নিয়োজিত করেছেন। প্রত্যেকটি আবর্তন করে এক নির্দিষ্ট মেয়াদ পর্যন্ত। ইনি আল্লাহ; তোমাদের পালনকর্তা, সাম্রাজ্য তাঁরই। তাঁর পরিবর্তে তোমরা যাদেরকে ডাক, তারা তুচ্ছ খেজুর আঁটিরও অধিকারী নয়।"},{"words":[{"a":"إِن","p":"in","b":"যদি"},{"a":"تَدۡعُوهُمۡ","p":"tad'uhum","b":"তোমরা তাদেরকে ডাকো"},{"a":"لَا","p":"la","b":"না"},{"a":"يَسۡمَعُواْ","p":"yasma'u","b":"তারা শুনতে পায়"},{"a":"دُعَآءَكُمۡ","p":"du'aakum","b":"তোমাদের ডাক"},{"a":"وَلَوۡ","p":"walaw","b":"আর যদি"},{"a":"سَمِعُواْ","p":"sami'u","b":"তারা শুনেও"},{"a":"مَا","p":"ma","b":"না"},{"a":"ٱسۡتَجَابُواْ","p":"is'tajabu","b":"তারা সাড়া দিতে পারে"},{"a":"لَكُمۡۖ","p":"lakum","b":"তোমাদেরকে"},{"a":"وَيَوۡمَ","p":"wayawma","b":"এবং দিনে"},{"a":"ٱلۡقِيَٰمَةِ","p":"al-qiyamati","b":"ক্বিয়ামাতের"},{"a":"يَكۡفُرُونَ","p":"yakfuruna","b":"তারা অস্বীকার করবে"},{"a":"بِشِرۡكِكُمۡۚ","p":"bishir'kikum","b":"তোমাদের শিরককে"},{"a":"وَلَا","p":"wala","b":"এবং না"},{"a":"يُنَبِّئُكَ","p":"yunabbi-uka","b":"তোমাকে জানাতে পারে কেউ"},{"a":"مِثۡلُ","p":"mith'lu","b":"মতো"},{"a":"خَبِيرٖ","p":"khabirin","b":"সর্বজ্ঞ আল্লাহর"}],"translation":"তোমরা তাদেরকে ডাকলে তারা তোমাদের সে ডাক শুনে না। শুনলেও তোমাদের ডাকে সাড়া দেয় না। কেয়ামতের দিন তারা তোমাদের শেরক অস্বীকার করবে। বস্তুতঃ আল্লাহর ন্যায় তোমাকে কেউ অবহিত করতে পারবে না।"},{"words":[{"a":"۞يَـٰٓأَيُّهَا","p":"yaayyuha","b":"হে"},{"a":"ٱلنَّاسُ","p":"al-nasu","b":"মানব সম্প্রদায়"},{"a":"أَنتُمُ","p":"antumu","b":"তোমরা"},{"a":"ٱلۡفُقَرَآءُ","p":"al-fuqarau","b":"মুখাপেক্ষী"},{"a":"إِلَى","p":"ila","b":"কাছে"},{"a":"ٱللَّهِۖ","p":"al-lahi","b":"আল্লাহর"},{"a":"وَٱللَّهُ","p":"wal-lahu","b":"কিন্তু আল্লাহ (এমন যে)"},{"a":"هُوَ","p":"huwa","b":"তিনিই"},{"a":"ٱلۡغَنِيُّ","p":"al-ghaniyu","b":"অভাবমুক্ত"},{"a":"ٱلۡحَمِيدُ","p":"al-hamidu","b":"প্রশংসিত"}],"translation":"হে মানুষ, তোমরা আল্লাহর গলগ্রহ। আর আল্লাহ; তিনি অভাবমুক্ত, প্রশংসিত।"},{"words":[{"a":"إِن","p":"in","b":"যদি"},{"a":"يَشَأۡ","p":"yasha","b":"তিনি ইচ্ছে করেন"},{"a":"يُذۡهِبۡكُمۡ","p":"yudh'hib'kum","b":"তোমাদেরকে বিলোপ করতে পারেন"},{"a":"وَيَأۡتِ","p":"wayati","b":"এবং আনতে পারেন (তোমাদের স্থানে)"},{"a":"بِخَلۡقٖ","p":"bikhalqin","b":"সৃষ্টিকে"},{"a":"جَدِيدٖ","p":"jadidin","b":"নতুন"}],"translation":"তিনি ইচ্ছা করলে তোমাদেরকে বিলুপ্ত করে এক নতুন সৃষ্টির উদ্ভব করবেন।"},{"words":[{"a":"وَمَا","p":"wama","b":"আর নয়"},{"a":"ذَٰلِكَ","p":"dhalika","b":"এটা"},{"a":"عَلَى","p":"ala","b":"জন্যে"},{"a":"ٱللَّهِ","p":"al-lahi","b":"আল্লাহর"},{"a":"بِعَزِيزٖ","p":"bi'azizin","b":"কোনো কঠিন (কিছু)"}],"translation":"এটা আল্লাহর পক্ষে কঠিন নয়।"},{"words":[{"a":"وَلَا","p":"wala","b":"এবং না"},{"a":"تَزِرُ","p":"taziru","b":"বহন করবে"},{"a":"وَازِرَةٞ","p":"waziratun","b":"কোনো বহনকারী"},{"a":"وِزۡرَ","p":"wiz'ra","b":"ভার"},{"a":"أُخۡرَىٰۚ","p":"ukh'ra","b":"অন্যের"},{"a":"وَإِن","p":"wa-in","b":"এবং যদি"},{"a":"تَدۡعُ","p":"tad'u","b":"ডাকে"},{"a":"مُثۡقَلَةٌ","p":"muth'qalatun","b":"কোনো বোঝাভারাক্রান্ত ব্যক্তি"},{"a":"إِلَىٰ","p":"ila","b":"দিকে"},{"a":"حِمۡلِهَا","p":"him'liha","b":"তার বোঝার (তা বইতে)"},{"a":"لَا","p":"la","b":"না"},{"a":"يُحۡمَلۡ","p":"yuh'mal","b":"বহন করা হবে"},{"a":"مِنۡهُ","p":"min'hu","b":"তার থেকে"},{"a":"شَيۡءٞ","p":"shayon","b":"(সামান্য) কিছুও"},{"a":"وَلَوۡ","p":"walaw","b":"এবং যদি"},{"a":"كَانَ","p":"kana","b":"সে হয়ও"},{"a":"ذَا","p":"dha","b":"আছে"},{"a":"قُرۡبَىٰٓۗ","p":"qur'ba","b":"কোন নিকট আত্মীয়"},{"a":"إِنَّمَا","p":"innama","b":"(তাই হে নাবী) কেবল"},{"a":"تُنذِرُ","p":"tundhiru","b":"তুমি সতর্ক করো"},{"a":"ٱلَّذِينَ","p":"alladhina","b":"(তাদেরকে) যারা"},{"a":"يَخۡشَوۡنَ","p":"yakhshawna","b":"ভয় করে"},{"a":"رَبَّهُم","p":"rabbahum","b":"তাদের রবকে"},{"a":"بِٱلۡغَيۡبِ","p":"bil-ghaybi","b":"না দেখা অবস্থায়"},{"a":"وَأَقَامُواْ","p":"wa-aqamu","b":"এবং প্রতিষ্ঠা করে"},{"a":"ٱلصَّلَوٰةَۚ","p":"al-salata","b":"সালাত"},{"a":"وَمَن","p":"waman","b":"এবং যে"},{"a":"تَزَكَّىٰ","p":"tazakka","b":"পবিত্র করে"},{"a":"فَإِنَّمَا","p":"fa-innama","b":"প্রকৃতপক্ষে"},{"a":"يَتَزَكَّىٰ","p":"yatazakka","b":"সে পবিত্র করে"},{"a":"لِنَفۡسِهِۦۚ","p":"linafsihi","b":"তার নিজের জন্যে"},{"a":"وَإِلَى","p":"wa-ila","b":"এবং দিকে"},{"a":"ٱللَّهِ","p":"al-lahi","b":"আল্লাহর-ই"},{"a":"ٱلۡمَصِيرُ","p":"al-masiru","b":"(তোমাদের হবে) প্রত্যাবর্তন"}],"translation":"কেউ অপরের বোঝা বহন করবে না। কেউ যদি তার গুরুতর ভার বহন করতে অন্যকে আহবান করে কেউ তা বহন করবে না-যদি সে নিকটবর্তী আত্নীয়ও হয়। আপনি কেবল তাদেরকে সতর্ক করেন, যারা তাদের পালনকর্তাকে না দেখেও ভয় করে এবং নামায কায়েম করে। যে কেউ নিজের সংশোধন করে, সে সংশোধন করে, স্বীয় কল্যাণের জন্যেই আল্লাহর নিকটই সকলের প্রত্যাবর্তন।"},{"words":[{"a":"وَمَا","p":"wama","b":"এবং না"},{"a":"يَسۡتَوِي","p":"yastawi","b":"সমান হয়"},{"a":"ٱلۡأَعۡمَىٰ","p":"al-a'ma","b":"অন্ধ"},{"a":"وَٱلۡبَصِيرُ","p":"wal-basiru","b":"ও চক্ষুষ্মান"}],"translation":"দৃষ্টিমান ও দৃষ্টিহীন সমান নয়।"},{"words":[{"a":"وَلَا","p":"wala","b":"এবং না"},{"a":"ٱلظُّلُمَٰتُ","p":"al-zulumatu","b":"অন্ধকারসমূহ"},{"a":"وَلَا","p":"wala","b":"আর না"},{"a":"ٱلنُّورُ","p":"al-nuru","b":"আলো"}],"translation":"সমান নয় অন্ধকার ও আলো।"}]