[{"words":[{"a":"بَلۡ","p":"bal","b":"\"(না) বরং"},{"a":"إِيَّاهُ","p":"iyyahu","b":"শুধু তাঁকেই"},{"a":"تَدۡعُونَ","p":"tad'una","b":"ডাকো তোমরা"},{"a":"فَيَكۡشِفُ","p":"fayakshifu","b":"অতঃপর তিনি দূর করেন"},{"a":"مَا","p":"ma","b":"যে জন্য"},{"a":"تَدۡعُونَ","p":"tad'una","b":"তোমরা ডাকো (দু'আ করো)"},{"a":"إِلَيۡهِ","p":"ilayhi","b":"কাছে তাঁর"},{"a":"إِن","p":"in","b":"যদি"},{"a":"شَآءَ","p":"shaa","b":"তিনি ইচ্ছে করেন"},{"a":"وَتَنسَوۡنَ","p":"watansawna","b":"এবং (তখন) তোমরা ভুলে যাও"},{"a":"مَا","p":"ma","b":"যাকে"},{"a":"تُشۡرِكُونَ","p":"tush'rikuna","b":"তোমরা শিরক করে থাকো\""}],"translation":"বরং তোমরা তো তাঁকেই ডাকবে। অতঃপর যে বিপদের জন্যে তাঁকে ডাকবে, তিনি ইচ্ছা করলে তা দুরও করে দেন। যাদেরকে অংশীদার করছ, তখন তাদেরকে ভুলে যাবে।"},{"words":[{"a":"وَلَقَدۡ","p":"walaqad","b":"এবং নিশ্চয়ই"},{"a":"أَرۡسَلۡنَآ","p":"arsalna","b":"পাঠিয়েছি আমরা (রাসূলগণকে)"},{"a":"إِلَىٰٓ","p":"ila","b":"প্রতি"},{"a":"أُمَمٖ","p":"umamin","b":"জাতিগুলোর)"},{"a":"مِّن","p":"min","b":"থেকে"},{"a":"قَبۡلِكَ","p":"qablika","b":"পূর্ব তোমার"},{"a":"فَأَخَذۡنَٰهُم","p":"fa-akhadhnahum","b":"অতঃপর আমরা ধরেছি তাদেরকে"},{"a":"بِٱلۡبَأۡسَآءِ","p":"bil-basai","b":"দিয়ে অর্থসংকট"},{"a":"وَٱلضَّرَّآءِ","p":"wal-darai","b":"ও দুঃখদৈন্য(দিয়ে)"},{"a":"لَعَلَّهُمۡ","p":"la'allahum","b":"যাতে তারা"},{"a":"يَتَضَرَّعُونَ","p":"yatadarra'una","b":"বিনীত হয়"}],"translation":"আর আমি আপনার পূর্ববর্তী উম্মতদের প্রতিও পয়গম্বর প্রেরণ করেছিলাম। অতঃপর আমি তাদেরকে অভাব-অনটন ও রোগ-ব্যধি দ্বারা পাকড়াও করেছিলাম যাতে তারা কাকুতি মিনতি করে।"},{"words":[{"a":"فَلَوۡلَآ","p":"falawla","b":"অতঃপর কেন না"},{"a":"إِذۡ","p":"idh","b":"যখন"},{"a":"جَآءَهُم","p":"jaahum","b":"এসেছিলো তাদের (কাছে)"},{"a":"بَأۡسُنَا","p":"basuna","b":"শাস্তি আমাদের"},{"a":"تَضَرَّعُواْ","p":"tadarra'u","b":"তারা বিনীত হলো"},{"a":"وَلَٰكِن","p":"walakin","b":"বরং"},{"a":"قَسَتۡ","p":"qasat","b":"শক্ত হয়ে গেলো"},{"a":"قُلُوبُهُمۡ","p":"qulubuhum","b":"অন্তরগুলো তাদের"},{"a":"وَزَيَّنَ","p":"wazayyana","b":"এবং সুশোভিত করেছিলো"},{"a":"لَهُمُ","p":"lahumu","b":"জন্যে তাদের"},{"a":"ٱلشَّيۡطَٰنُ","p":"al-shaytanu","b":"শয়তান"},{"a":"مَا","p":"ma","b":"যা"},{"a":"كَانُواْ","p":"kanu","b":"তারা ছিলো"},{"a":"يَعۡمَلُونَ","p":"ya'maluna","b":"কাজ করতে"}],"translation":"অতঃপর তাদের কাছে যখন আমার আযাব আসল, তখন কেন কাকুতি-মিনতি করল না ? বস্তুতঃ তাদের অন্তর কঠোর হয়ে গেল এবং শয়তান তাদের কাছে সুশোভিত করে দেখাল, যে কাজ তারা করছিল।"},{"words":[{"a":"فَلَمَّا","p":"falamma","b":"অতঃপর যখন"},{"a":"نَسُواْ","p":"nasu","b":"তারা ভুলে গেল"},{"a":"مَا","p":"ma","b":"যা"},{"a":"ذُكِّرُواْ","p":"dhukkiru","b":"তাদের উপদেশ দেয়া হয়েছিলো"},{"a":"بِهِۦ","p":"bihi","b":"সম্পর্কে সে"},{"a":"فَتَحۡنَا","p":"fatahna","b":"তখন খুলে দিলাম আমরা"},{"a":"عَلَيۡهِمۡ","p":"alayhim","b":"উপর তাদের"},{"a":"أَبۡوَٰبَ","p":"abwaba","b":"(স্বচ্ছলতার) দরজাসমূহ"},{"a":"كُلِّ","p":"kulli","b":"সব"},{"a":"شَيۡءٍ","p":"shayin","b":"কিছুর"},{"a":"حَتَّىٰٓ","p":"hatta","b":"এমনকি"},{"a":"إِذَا","p":"idha","b":"যখন"},{"a":"فَرِحُواْ","p":"farihu","b":"তারা উল্লসিত হলো"},{"a":"بِمَآ","p":"bima","b":"নিয়ে তা যা"},{"a":"أُوتُوٓاْ","p":"utu","b":"তাদের দেয়া হয়েছিলো"},{"a":"أَخَذۡنَٰهُم","p":"akhadhnahum","b":"আমরা ধরলাম তাদের"},{"a":"بَغۡتَةٗ","p":"baghtatan","b":"হঠাৎ"},{"a":"فَإِذَا","p":"fa-idha","b":"ফলে তখন"},{"a":"هُم","p":"hum","b":"তারা"},{"a":"مُّبۡلِسُونَ","p":"mub'lisuna","b":"নিরাশ হয়ে পড়লো"}],"translation":"অতঃপর তারা যখন ঐ উপদেশ ভুলে গেল, যা তাদেরকে দেয়া হয়েছিল, তখন আমি তাদের সামনে সব কিছুর দ্বার উম্মুক্ত করে দিলাম। এমনকি, যখন তাদেরকে প্রদত্ত বিষয়াদির জন্যে তারা খুব গর্বিত হয়ে পড়ল, তখন আমি অকস্মাৎ তাদেরকে পাকড়াও করলাম। তখন তারা নিরাশ হয়ে গেল।"},{"words":[{"a":"فَقُطِعَ","p":"faquti'a","b":"অতঃপর উচ্ছেদ করা হলো"},{"a":"دَابِرُ","p":"dabiru","b":"মূল"},{"a":"ٱلۡقَوۡمِ","p":"al-qawmi","b":"(ঐ)সম্প্রদায়ের"},{"a":"ٱلَّذِينَ","p":"alladhina","b":"যারা"},{"a":"ظَلَمُواْۚ","p":"zalamu","b":"সীমালঙ্ঘন করেছিলো"},{"a":"وَٱلۡحَمۡدُ","p":"wal-hamdu","b":"আর সব প্রশংসা"},{"a":"لِلَّهِ","p":"lillahi","b":"জন্যে আল্লাহরই"},{"a":"رَبِّ","p":"rabbi","b":"(যিনি) রব"},{"a":"ٱلۡعَٰلَمِينَ","p":"al-'alamina","b":"বিশ্বজগতের"}],"translation":"অতঃপর জালেমদের মূল শিকড় কর্তিত হল। সমস্ত প্রশংসা আল্লাহরই জন্যে, যিনি বিশ্বজগতের পালনকর্তা।"},{"words":[{"a":"قُلۡ","p":"qul","b":"বলো"},{"a":"أَرَءَيۡتُمۡ","p":"ara-aytum","b":"\"কি (ভেবে) দেখছো তোমরা"},{"a":"إِنۡ","p":"in","b":"যদি"},{"a":"أَخَذَ","p":"akhadha","b":"কেড়ে নেন"},{"a":"ٱللَّهُ","p":"al-lahu","b":"আল্লাহ"},{"a":"سَمۡعَكُمۡ","p":"sam'akum","b":"শ্রবণশক্তি তোমাদের"},{"a":"وَأَبۡصَٰرَكُمۡ","p":"wa-absarakum","b":"ও দৃষ্টিশক্তি তোমাদের"},{"a":"وَخَتَمَ","p":"wakhatama","b":"এবং সিল লাগান"},{"a":"عَلَىٰ","p":"ala","b":"উপর"},{"a":"قُلُوبِكُم","p":"qulubikum","b":"অন্তরগুলোর তোমাদের"},{"a":"مَّنۡ","p":"man","b":"কোনো"},{"a":"إِلَٰهٌ","p":"ilahun","b":"ইলাহ (আছে)"},{"a":"غَيۡرُ","p":"ghayru","b":"ছাড়া"},{"a":"ٱللَّهِ","p":"al-lahi","b":"আল্লাহ (যে)"},{"a":"يَأۡتِيكُم","p":"yatikum","b":"কাছে আসবে তোমাদের"},{"a":"بِهِۗ","p":"bihi","b":"নিয়ে তা"},{"a":"ٱنظُرۡ","p":"unzur","b":"দেখো"},{"a":"كَيۡفَ","p":"kayfa","b":"কেমনভাবে"},{"a":"نُصَرِّفُ","p":"nusarrifu","b":"বারবার বর্ণনা করি আমরা"},{"a":"ٱلۡأٓيَٰتِ","p":"al-ayati","b":"নিদর্শনগুলো"},{"a":"ثُمَّ","p":"thumma","b":"এরপরও"},{"a":"هُمۡ","p":"hum","b":"তারা"},{"a":"يَصۡدِفُونَ","p":"yasdifuna","b":"তারা মুখ ফিরিয়ে নেয়\""}],"translation":"আপনি বলুনঃ বল তো দেখি, যদি আল্লাহ তোমাদের কান ও চোখ নিয়ে যান এবং তোমাদের অন্তরে মোহর এঁটে দেন, তবে এবং তোমাদের আল্লাহ ব্যতীত এমন উপাস্য কে আছে, যে তোমাদেরকে এগুলো এনে দেবে? দেখ, আমি কিভাবে ঘুরিয়ে-ফিরিয়ে নিদর্শনাবলী বর্ণনা করি। তথাপি তারা বিমুখ হচ্ছে।"},{"words":[{"a":"قُلۡ","p":"qul","b":"বলো"},{"a":"أَرَءَيۡتَكُمۡ","p":"ara-aytakum","b":"\"(ভেবে) দেখছো কি তোমরা"},{"a":"إِنۡ","p":"in","b":"যদি"},{"a":"أَتَىٰكُمۡ","p":"atakum","b":"কাছে এসে পড়ে তোমাদের"},{"a":"عَذَابُ","p":"adhabu","b":"শাস্তি"},{"a":"ٱللَّهِ","p":"al-lahi","b":"আল্লাহর"},{"a":"بَغۡتَةً","p":"baghtatan","b":"হঠাৎ"},{"a":"أَوۡ","p":"aw","b":"বা"},{"a":"جَهۡرَةً","p":"jahratan","b":"প্রকাশ্যে"},{"a":"هَلۡ","p":"hal","b":"কি"},{"a":"يُهۡلَكُ","p":"yuh'laku","b":"ধ্বংস করা হবে"},{"a":"إِلَّا","p":"illa","b":"এ ছাড়া"},{"a":"ٱلۡقَوۡمُ","p":"al-qawmu","b":"(যারা)সম্প্রদায়"},{"a":"ٱلظَّـٰلِمُونَ","p":"al-zalimuna","b":"সীমালঙ্ঘনকারী"}],"translation":"বলে দিনঃ দেখতো, যদি আল্লাহর শাস্তি, আকস্মিক কিংবা প্রকাশ্যে তোমাদের উপর আসে, তবে জালেম, সম্প্রদায় ব্যতীত কে ধ্বংস হবে?"},{"words":[{"a":"وَمَا","p":"wama","b":"এবং না"},{"a":"نُرۡسِلُ","p":"nur'silu","b":"আমরা পাঠিয়েছি"},{"a":"ٱلۡمُرۡسَلِينَ","p":"al-mur'salina","b":"রাসূলগণকে"},{"a":"إِلَّا","p":"illa","b":"এ ছাড়া যে"},{"a":"مُبَشِّرِينَ","p":"mubashirina","b":"সুসংবাদদাতা"},{"a":"وَمُنذِرِينَۖ","p":"wamundhirina","b":"ও সতর্ককারী (হিসেবে)"},{"a":"فَمَنۡ","p":"faman","b":"অতএব যে"},{"a":"ءَامَنَ","p":"amana","b":"ঈমান আনবে"},{"a":"وَأَصۡلَحَ","p":"wa-aslaha","b":"ও সংশোধন করবে"},{"a":"فَلَا","p":"fala","b":"সেক্ষেত্রে নেই"},{"a":"خَوۡفٌ","p":"khawfun","b":"কোনো ভয়"},{"a":"عَلَيۡهِمۡ","p":"alayhim","b":"উপর তাদের"},{"a":"وَلَا","p":"wala","b":"আর না"},{"a":"هُمۡ","p":"hum","b":"তারা"},{"a":"يَحۡزَنُونَ","p":"yahzanuna","b":"দুঃখিত হবে"}],"translation":"আমি পয়গম্বরদেরকে প্রেরণ করি না, কিন্তু সুসংবাদাতা ও ভীতি প্রদর্শকরূপে অতঃপর যে বিশ্বাস স্থাপন করে এবং সংশোধিত হয়, তাদের কোন শঙ্কা নেই এবং তারা দুঃখিত হবে না।"},{"words":[{"a":"وَٱلَّذِينَ","p":"wa-alladhina","b":"এবং যারা"},{"a":"كَذَّبُواْ","p":"kadhabu","b":"মিথ্যারোপ করেছে"},{"a":"بِـَٔايَٰتِنَا","p":"biayatina","b":"প্রতি নিদর্শনগুলোর আমার"},{"a":"يَمَسُّهُمُ","p":"yamassuhumu","b":"স্পর্শ করবে তাদের"},{"a":"ٱلۡعَذَابُ","p":"al-'adhabu","b":"শাস্তি"},{"a":"بِمَا","p":"bima","b":"এ কারণে যে"},{"a":"كَانُواْ","p":"kanu","b":"তারা ছিলো"},{"a":"يَفۡسُقُونَ","p":"yafsuquna","b":"তারা সত্যত্যাগ করে"}],"translation":"যারা আমার নিদর্শনাবলীকে মিথ্যা বলে, তাদেরকে তাদের নাফরমানীর কারণে আযাব স্পর্শ করবে।"},{"words":[{"a":"قُل","p":"qul","b":"(হে নাবী) বলো"},{"a":"لَّآ","p":"la","b":"\"না"},{"a":"أَقُولُ","p":"aqulu","b":"\"আমি বলি"},{"a":"لَكُمۡ","p":"lakum","b":"উদ্দেশ্যে তোমাদের (যে)"},{"a":"عِندِي","p":"indi","b":"কাছে আমার (আছে)"},{"a":"خَزَآئِنُ","p":"khazainu","b":"ধনভান্ডারসমূহ"},{"a":"ٱللَّهِ","p":"al-lahi","b":"আল্লাহর"},{"a":"وَلَآ","p":"wala","b":"এবং না"},{"a":"أَعۡلَمُ","p":"a'lamu","b":"জানি আমি"},{"a":"ٱلۡغَيۡبَ","p":"al-ghayba","b":"অদৃশ্যকে"},{"a":"وَلَآ","p":"wala","b":"এবং না"},{"a":"أَقُولُ","p":"aqulu","b":"বলি আমি"},{"a":"لَكُمۡ","p":"lakum","b":"উদ্দেশ্যে তোমাদের (যে)"},{"a":"إِنِّي","p":"inni","b":"নিশ্চয়ই আমি"},{"a":"مَلَكٌۖ","p":"malakun","b":"ফেরেশতা"},{"a":"إِنۡ","p":"in","b":"(প্রকৃতপক্ষে) না"},{"a":"أَتَّبِعُ","p":"attabi'u","b":"অনুসরণ করি আমি"},{"a":"إِلَّا","p":"illa","b":"এ ছাড়া"},{"a":"مَا","p":"ma","b":"যা"},{"a":"يُوحَىٰٓ","p":"yuha","b":"ওহী করা হয়"},{"a":"إِلَيَّۚ","p":"ilayya","b":"আমার প্রতি\""},{"a":"قُلۡ","p":"qul","b":"বলো"},{"a":"هَلۡ","p":"hal","b":"\"কি"},{"a":"يَسۡتَوِي","p":"yastawi","b":"সমান হয়"},{"a":"ٱلۡأَعۡمَىٰ","p":"al-a'ma","b":"অন্ধ"},{"a":"وَٱلۡبَصِيرُۚ","p":"wal-basiru","b":"আর চক্ষুষ্মান\""},{"a":"أَفَلَا","p":"afala","b":"কি তবে না"},{"a":"تَتَفَكَّرُونَ","p":"tatafakkaruna","b":"তোমরা চিন্তা করো"}],"translation":"আপনি বলুনঃ আমি তোমাদেরকে বলি না যে, আমার কাছে আল্লাহর ভান্ডার রয়েছে। তাছাড়া আমি অদৃশ্য বিষয় অবগতও নই। আমি এমন বলি না যে, আমি ফেরেশতা। আমি তো শুধু ঐ ওহীর অনুসরণ করি, যা আমার কাছে আসে। আপনি বলে দিনঃ অন্ধ ও চক্ষুমান কি সমান হতে পারে? তোমরা কি চিন্তা কর না ?"}]