[{"words":[{"a":"قَالَ","p":"qala","b":"তিনি বললেন"},{"a":"هَٰذَا","p":"hadha","b":"\"এটা"},{"a":"صِرَٰطٌ","p":"siratun","b":"পথ"},{"a":"عَلَيَّ","p":"alayya","b":"আমার দিকে"},{"a":"مُسۡتَقِيمٌ","p":"mus'taqimun","b":"সরল"}],"translation":"আল্লাহ বললেনঃ এটা আমা পর্যন্ত সোজা পথ।"},{"words":[{"a":"إِنَّ","p":"inna","b":"নিশ্চয়ই (যারা)"},{"a":"عِبَادِي","p":"ibadi","b":"আমার দাসরা"},{"a":"لَيۡسَ","p":"laysa","b":"নেই"},{"a":"لَكَ","p":"laka","b":"তোমার জন্যে"},{"a":"عَلَيۡهِمۡ","p":"alayhim","b":"তাদের উপর"},{"a":"سُلۡطَٰنٌ","p":"sul'tanun","b":"কোন প্রভাব"},{"a":"إِلَّا","p":"illa","b":"এ ছাড়া"},{"a":"مَنِ","p":"mani","b":"যে"},{"a":"ٱتَّبَعَكَ","p":"ittaba'aka","b":"তোমার অনুসরণ করবে"},{"a":"مِنَ","p":"mina","b":"থেকে"},{"a":"ٱلۡغَاوِينَ","p":"al-ghawina","b":"পথভ্রষ্ট\""}],"translation":"যারা আমার বান্দা, তাদের উপর তোমার কোন ক্ষমতা নেই; কিন্তু পথভ্রান্তদের মধ্য থেকে যারা তোমার পথে চলে।"},{"words":[{"a":"وَإِنَّ","p":"wa-inna","b":"এবং নিশ্চয়ই"},{"a":"جَهَنَّمَ","p":"jahannama","b":"জাহান্নাম"},{"a":"لَمَوۡعِدُهُمۡ","p":"lamaw'iduhum","b":"অবশ্যই প্রতিশ্রুত স্হান তাদের"},{"a":"أَجۡمَعِينَ","p":"ajma'ina","b":"সকলের"}],"translation":"তাদের সবার নির্ধারিত স্থান হচ্ছে জাহান্নাম।"},{"words":[{"a":"لَهَا","p":"laha","b":"তার আছে"},{"a":"سَبۡعَةُ","p":"sab'atu","b":"সাতটি"},{"a":"أَبۡوَٰبٖ","p":"abwabin","b":"দরজা"},{"a":"لِّكُلِّ","p":"likulli","b":"জন্যে প্রত্যেকটির"},{"a":"بَابٖ","p":"babin","b":"দরজার"},{"a":"مِّنۡهُمۡ","p":"min'hum","b":"তাদের থেকে"},{"a":"جُزۡءٞ","p":"juz'on","b":"অংশ (দল)"},{"a":"مَّقۡسُومٌ","p":"maqsumun","b":"পৃথক পৃথক"}],"translation":"এর সাতটি দরজা আছে। প্রত্যেক দরজার জন্যে এক একটি পৃথক দল আছে।"},{"words":[{"a":"إِنَّ","p":"inna","b":"নিশ্চয়ই"},{"a":"ٱلۡمُتَّقِينَ","p":"al-mutaqina","b":"মুত্তাকীরা"},{"a":"فِي","p":"fi","b":"মধ্যে (থাকবে)"},{"a":"جَنَّـٰتٖ","p":"jannatin","b":"জান্নাতের"},{"a":"وَعُيُونٍ","p":"wa'uyunin","b":"ও ঝর্ণাধারাসমূহের"}],"translation":"নিশ্চয় খোদাভীরুরা বাগান ও নির্ঝরিনীসহূহে থাকবে।"},{"words":[{"a":"ٱدۡخُلُوهَا","p":"ud'khuluha","b":"\"তাতে তোমরা প্রবেশ করো"},{"a":"بِسَلَٰمٍ","p":"bisalamin","b":"সাথে শান্তির"},{"a":"ءَامِنِينَ","p":"aminina","b":"নিরাপদে\""}],"translation":"বলা হবেঃ এগুলোতে নিরাপত্তা ও শান্তি সহকরে প্রবেশ কর।"},{"words":[{"a":"وَنَزَعۡنَا","p":"wanaza'na","b":"এবং আমরা দূর করে দিবো"},{"a":"مَا","p":"ma","b":"যা"},{"a":"فِي","p":"fi","b":"মধ্যে আছে"},{"a":"صُدُورِهِم","p":"sudurihim","b":"তাদের অন্তরসমূহের"},{"a":"مِّنۡ","p":"min","b":"থেকে"},{"a":"غِلٍّ","p":"ghillin","b":"ঈর্ষা"},{"a":"إِخۡوَٰنًا","p":"ikh'wanan","b":"ভাই ভাই হয়ে (তারা বসবে)"},{"a":"عَلَىٰ","p":"ala","b":"উপর"},{"a":"سُرُرٖ","p":"sururin","b":"আসনসমূহের"},{"a":"مُّتَقَٰبِلِينَ","p":"mutaqabilina","b":"মুখোমুখি হয়ে"}],"translation":"তাদের অন্তরে যে ক্রোধ ছিল, আমি তা দূর করে দেব। তারা ভাই ভাইয়ের মত সামনা-সামনি আসনে বসবে।"},{"words":[{"a":"لَا","p":"la","b":"না"},{"a":"يَمَسُّهُمۡ","p":"yamassuhum","b":"তাদের স্পর্শ করবে"},{"a":"فِيهَا","p":"fiha","b":"তার মধ্যে"},{"a":"نَصَبٞ","p":"nasabun","b":"কোনো অবসাদ"},{"a":"وَمَا","p":"wama","b":"আছে  না"},{"a":"هُم","p":"hum","b":"তারা"},{"a":"مِّنۡهَا","p":"min'ha","b":"তা থেকে"},{"a":"بِمُخۡرَجِينَ","p":"bimukh'rajina","b":"বহিষ্কৃত হবে"}],"translation":"সেখানে তাদের মোটেই কষ্ট হবে না এবং তারা সেখান থেকে বহিস্কৃত হবে না।"},{"words":[{"a":"۞نَبِّئۡ","p":"nabbi","b":"জানিয়ে দাও"},{"a":"عِبَادِيٓ","p":"ibadi","b":"আমার দাসদের"},{"a":"أَنِّيٓ","p":"anni","b":"যে আমি"},{"a":"أَنَا","p":"ana","b":"আমিই"},{"a":"ٱلۡغَفُورُ","p":"al-ghafuru","b":"ক্ষমাশীল"},{"a":"ٱلرَّحِيمُ","p":"al-rahimu","b":"পরম দয়ালু"}],"translation":"আপনি আমার বান্দাদেরকে জানিয়ে দিন যে, আমি অত্যন্ত ক্ষমাশীল দয়ালু।"},{"words":[{"a":"وَأَنَّ","p":"wa-anna","b":"এবং (এও) যে"},{"a":"عَذَابِي","p":"adhabi","b":"আমার শাস্তিও"},{"a":"هُوَ","p":"huwa","b":"তা"},{"a":"ٱلۡعَذَابُ","p":"al-'adhabu","b":"শাস্তি"},{"a":"ٱلۡأَلِيمُ","p":"al-alimu","b":"নিদারুণ"}],"translation":"এবং ইহাও যে, আমার শাস্তিই যন্ত্রনাদায়ক শাস্তি।"}]