[{"words":[{"a":"كَلَّا","p":"kalla","b":"কক্ষন না"},{"a":"لَا","p":"la","b":"নাই"},{"a":"وَزَرَ","p":"wazara","b":"আশ্রয় স্থল"}],"translation":"না কোথাও আশ্রয়স্থল নেই।"},{"words":[{"a":"إِلَىٰ","p":"ila","b":"দিকে"},{"a":"رَبِّكَ","p":"rabbika","b":"তোমার রবের"},{"a":"يَوۡمَئِذٍ","p":"yawma-idhin","b":"সেদিন"},{"a":"ٱلۡمُسۡتَقَرُّ","p":"al-mus'taqaru","b":"অবস্থানহল"}],"translation":"আপনার পালনকর্তার কাছেই সেদিন ঠাঁই হবে।"},{"words":[{"a":"يُنَبَّؤُاْ","p":"yunabba-u","b":"জানিয়ে দেয়া হবে"},{"a":"ٱلۡإِنسَٰنُ","p":"al-insanu","b":"মানুষ কে"},{"a":"يَوۡمَئِذِۭ","p":"yawma-idhin","b":"সেদিন"},{"a":"بِمَا","p":"bima","b":"যা ওই বিষয়ে"},{"a":"قَدَّمَ","p":"qaddama","b":"সে আগে পাঠিয়েছে"},{"a":"وَأَخَّرَ","p":"wa-akhara","b":"এবং পিছে ছেড়েছে"}],"translation":"সেদিন মানুষকে অবহিত করা হবে সে যা সামনে প্রেরণ করেছে ও পশ্চাতে ছেড়ে দিয়েছে।"},{"words":[{"a":"بَلِ","p":"bali","b":"বরং"},{"a":"ٱلۡإِنسَٰنُ","p":"al-insanu","b":"মানুষ"},{"a":"عَلَىٰ","p":"ala","b":"সম্পর্কে"},{"a":"نَفۡسِهِۦ","p":"nafsihi","b":"তার নিজের"},{"a":"بَصِيرَةٞ","p":"basiratun","b":"খুব অবগত"}],"translation":"বরং মানুষ নিজেই তার নিজের সম্পর্কে চক্ষুমান।"},{"words":[{"a":"وَلَوۡ","p":"walaw","b":"এবং যদিও"},{"a":"أَلۡقَىٰ","p":"alqa","b":"পেশ করে সে"},{"a":"مَعَاذِيرَهُۥ","p":"ma'adhirahu","b":"তার অজুহাত সমূহ"}],"translation":"যদিও সে তার অজুহাত পেশ করতে চাইবে।"},{"words":[{"a":"لَا","p":"la","b":"না"},{"a":"تُحَرِّكۡ","p":"tuharrik","b":"নাড়াবে"},{"a":"بِهِۦ","p":"bihi","b":"এর সাথে"},{"a":"لِسَانَكَ","p":"lisanaka","b":"তোমার জিহ্বা"},{"a":"لِتَعۡجَلَ","p":"lita'jala","b":"তাড়াতাড়ির জন্য"},{"a":"بِهِۦٓ","p":"bihi","b":"এর সাথে"}],"translation":"তাড়াতাড়ি শিখে নেয়ার জন্যে আপনি দ্রুত ওহী আবৃত্তি করবেন না।"},{"words":[{"a":"إِنَّ","p":"inna","b":"নিশ্চয়"},{"a":"عَلَيۡنَا","p":"alayna","b":"আমাদের দায়িত্ব"},{"a":"جَمۡعَهُۥ","p":"jam'ahu","b":"তা মুখস্ত করান"},{"a":"وَقُرۡءَانَهُۥ","p":"waqur'anahu","b":"এবং তা পাঠ করান"}],"translation":"এর সংরক্ষণ ও পাঠ আমারই দায়িত্ব।"},{"words":[{"a":"فَإِذَا","p":"fa-idha","b":"যখন অতঃপর"},{"a":"قَرَأۡنَٰهُ","p":"qaranahu","b":"তা আমরা পড়ি"},{"a":"فَٱتَّبِعۡ","p":"fa-ittabi'","b":"অনিুসরণ তখন করো"},{"a":"قُرۡءَانَهُۥ","p":"qur'anahu","b":"তা পাঠের"}],"translation":"অতঃপর আমি যখন তা পাঠ করি, তখন আপনি সেই পাঠের অনুসরণ করুন।"},{"words":[{"a":"ثُمَّ","p":"thumma","b":"অতঃপর"},{"a":"إِنَّ","p":"inna","b":"নিশ্চয়"},{"a":"عَلَيۡنَا","p":"alayna","b":"আমাদের দায়িত্ব"},{"a":"بَيَانَهُۥ","p":"bayanahu","b":"তা ব্যাখ্যা দেয়া"}],"translation":"এরপর বিশদ বর্ণনা আমারই দায়িত্ব।"},{"words":[{"a":"كَلَّا","p":"kalla","b":"কক্ষন না"},{"a":"بَلۡ","p":"bal","b":"বরং"},{"a":"تُحِبُّونَ","p":"tuhibbuna","b":"তোমরা পছন্দ করো"},{"a":"ٱلۡعَاجِلَةَ","p":"al-'ajilata","b":"পার্থিব জীবন"}],"translation":"কখনও না, বরং তোমরা পার্থিব জীবনকে ভালবাস"}]